{
  "sourceType": "livre",
  "subject": "mathematiques",
  "grade": "3eme",
  "chapter": "puissances_racines_carrees",
  "title": "t l charger 20 62 mb - part 20",
  "content": "Connaître la formule du cosinus voirformulaireê 1ô p. 307\n\nKLM est un triangle rectangle en K. Le cosinus de l'angle KLM est égal à...\n\ncôté opposé à KLM\n\nhypoténuse\n\n^ côté adjacent à KLM\n\nhypoténuse\n\nhypoténuse\n\nUtiliser la calculatrice voir formulaire g 1 ô p. 307\n\nL'arrondi au degré de la mesure de l'angle BAC\n\ndu triangle rectangle ci-contre est...\n\na. 48° b. 1° c. 54°\n\nUtiliser un cosinus •* voirformulaireg 1ôp. 307\n\nMNP est un triangle rectangle en M tel que:\n\nMPN =30° et MP = 2 cm\n\nLa longueur NP de l'hypoténuse est égale à...\n\na. 2 x cos 30° b. (cos 30°) : 2 c.\n\ncôté adjacent à KLM\n\ncos30°\n\n2 m\n\nft/oiv les v-affeh\n\nde tours da^s\n\nle -forimulaire\n\net les exercices\n\nde soutien\n\nVl numérique-\n\nDans chaque cas, déterminer mentalement si les mesures sont celles de deux angles\n\ncomplémentaires, supplémentaires ou ni l'un ni l'autre.\n\na. 49° et 41° b. 32° et 68° c. 87° et 93° d. 26° et 64° e. 55° et 35°\n\nCHAPITRE 11 «Triangles rectangles. Trigonométrie 209\n\nCosinus, sinus, tangente d'un angle aigu\n\nConjecturer avec un logiciel\n\na. Avec le logiciel GeoGebra, créer un curseur a (cocher\n\nAngle) allant de 0° à 90° avec un pas de 10.\n\nb. Tracer un triangle ABC rectangle en A tel que ABC = a\n\n(utiliser ^ j pour tracer la demi-droite [BC)).\n\nC. Afficher les longueurs des côtés du triangle.\n\nd. Dans la zone de saisie, taper l'instruction ci-contre.\n\nA D\n\nQue représente le rapport ^ pour l'angle ABC ?\n\n□ C\n\ne. Afficher de même les rapports et 4^.\n\nBC AB\n\nDéplacer le point A. Que constate-t-on pour les rapports\n\naffichés? Que peut-on conjecturer?\n\n1— c -\n\nAB * B C ^ 0.88\n\nAC/BC-0.47\n\n0 = 38*\n\nBC =5.70\n\nCA = 2.71\n\nAC / AB = 0.53\n\nBA = 5 J\n\nSaisie. 'ABfBC\"\"-»-(Dîstanc«lA,B]iDlstance[B.CI)\n\n0 Démontrer les conjectures\n\nABC et A'BC sont deux triangles rectangles en A et A' qui ont un\n\nangle aigu en commun.\n\na. Paul affirme: « Je reconnais une configuration de Thalès ».\n\nJustifier cette affirmation.\n\nb. Quelles égalités de rapports peut-on écrire alors ? B\n\nc. Recopier et compléter: «On sait que ■lê- = -A^7 donc BCx ... = ACx ...\n\nDL A L\n\nPar conséquent, = Ainsi le rapportne dépend que de ...».\n\nd. De façon analogue, à partir de -|j^ = -^7, démontrer que =\n\nDans un triangle ABC rectangle en A, on note :\n\n• cos ABC = £4;\n\ndC\n\n(« cosinus de ABC »)\n\n• sin ABC = AC\n\nBC '\n\n{« sinus de ABC »)\n\n• tan ABC = 4i-\n\nAt>\n\n{« tangente de ABC ») p\n\nA'\n\n\\>\n\nr:\n\nCôté\n\nopposé\n\nà ABC\n\nCôté adjacent ^\n\nà ABC\n\n0 Calculer des longueurs\n\nPemsev à met-tv-e\n\nla taldula-tvide ,\n\ncm mode\n\nUne échelle de 3,20 m de long est appuyée contre un mur vertical comme\n\nPar mesure de sécurité, l'angle que fait l'échelle avec le sol doit être de 75°.\n\na. Avec les notations de la figure, expliquer pourquoi AB = 3,2 x sin 75°.\n\nb. Avec la touche sin de la calculatrice, donner l'arrondi au centimètre de\n\nla longueur AB.\n\nC. Déterminer de deux façons différentes une valeur approchée de la\n\nlongueur BC.\n\nMur\n\ni_\n\n210\n\nQ Déterminer un angle\n\nPtmsev- à metbre\n\nla taltula-tvite ,\n\ncm mode DE^jRt.\n\nPour battre le record du monde du plus long saut en rollers,\n\nTaïg Khris s'est élancé sur une rampe dont la partie plane\n\nmesurait 40 m de long pour une hauteur de 9 m.\n\nDéterminer la valeur approchée par défaut au degré près de la\n\nmesure de l'angle entre la rampe et l'horizontale.\n\nen\n\nUtiliser la trigonométrie\n\nCela signifie\n\nque si la route\n\nentre les deux\n\nsommets\n\nétait une\n\nligne droite\n\nde 8 484 m,\n\nelle aurait une\n\npente\n\nde 6,9 %\n\n1. Pente et angle\n\nLa pente d'une route est le quotient du dénivelé par la dis-\n\ntance horizontale parcourue. Elle s'exprime en %.\n\na. On note a l'angle de la route par rapport à l'horizontale.\n\nQue représente la pente de la route pour l'angle oc?\n\nb. Une montée a une pente de 15%. Déterminer la valeur\n\napprochée par défaut au dixième de degré près de la mesure\n\nde l'angle d'élévation de la route.\n\n2. Le Tour de France\n\nLe 21 juillet 2011, les coureurs du Tour de France ont gravi\n\nla route qui va du col du Lautaret au col du Galibier dans\n\nles Alpes.\n\nLa distance entre les deux cols est de 8484 m avec une\n\npente moyenne de 6,9%.\n\nSachant que le Lautaret culmine à 2058 m, calculer une\n\nvaleur approchée à 1 m près de l'altitude du Galibier.\n\nCD\n\nCD\n\nDistance horizontale parcourue\n\nCol du\n\nLauraret fi\".\n\nCol du Galibier\n\nlOJT\n\nÂ\n\nr *■\n\nP -fi- 'fW '\n\n;•\n\nJ6 «\n\n0 Effectuer des constructions\n\na. Avec une équerre graduée et un compas, construire des angles aigus xEy, fMz, uTv tels que\n\n• sin fMz = y\n\n« cos xEy-^\n\nb. Est-il possible de construire un angle aigu x'Ky' tel que sin x Kj' =f ?\n\nC. Est-il possible de construire un angle aigu f'Fz' tel que tan f'Fz' =27\n\n■»tan uJv =\n\nDeux formules de trigonométrie\n\nÉtablir des relations entre cosinus, sinus, tangente\n\nABC est un triangle rectangle en A; on note ô = ABC.\n\na. Donner les expressions de cos ô, sin â et tan ô dans ce triangle.\n\nb. Écrire l'égalité de Pythagore dans ce triangle rectangle.\n\nC. Démontrer que (cos â)2 + (sin â)2= 1.\n\nd. Démontrer que: tana =\n\nsm a\n\ncos â\n\nCette égalité\n\ns'eévi-fc aussi\n\ntosïô + si^2- O —1.\n\nLa trigonométrie\n\n(du grec trigonos :\n\ntriangulaire et métron\n\nmesure) traite des\n\nrapports entre\n\ndistances et angles\n\ndans un triangle\n\nrectangle.\n\nCHAPITRE 11 «Triangles rectangles. Trigonométrie 211\n\nCosinus, sinus, tangente d'un angle aigu\n\nDans un triangle rectangle,\n\nle cosinus d'un angle aigu est le quotient\n\nlongueur du côté adjacent à cet angle\n\nlongueur de l'hypoténuse\n\n. . _ . «.• «. longueur du côté opposé à cet angle\n\n• le sinus d un angle aigu est le quotient —r . 7 — ;\n\nlongueur de I hypoténuse\n\n, . , - 4. longueur du côté opposé à cet angle\n\n• la tangente d un angle aigu est le quotient t—^ 7——— 7\n\nlongueur du cote adjacent a cet angle\n\nDans un triangle ABC rectangle en A:\n\n• cos ABC = (lire « cosinus de ABC »)\n\n• sin ABC = (lire « sinus de ABC »)\n\n• tan ABC = ^ (lire « tangente de ABC ») D Côté adjacent\n\nà ABC\n\nMémorisation de ces formules: on peut retenir l'expression SOHCAHTOA.\n\ncN\n\nSOH\n\nCAH\n\nTOA\n\n« Le Sinus est égal à côté Opposé sur Hypoténuse »\n\n« Le Cosinus est égal à côté Adjacent sur Hypoténuse »\n\n« La Tangente est égale à côté Opposé sur côté Adjacent ».\n\nCôté\n\nopposé\n\nà ABC\n\nRemarques : • Un cosinus, un sinus, une tangente n'ont pas d'unité.\n\n• cos ABC, sin ABC, tan ABC sont des nombres strictement positifs (puisque ce sont des rapports\n\nde longueurs). De plus, l'hypoténuse est le côté le plus long d'un triangle ABC rectangle en A.\n\nAinsi, pour calculer cos ABC ou sin ABC, on divise une longueur par une longueur plus grande.\n\nDonc 0 < cos ABC <1 et 0 < sin ABC < 1.\n\nQ Deux formules de trigonométrie\n\nâ désigne un angle aigu d'un triangle rectangle.\n\n(1) cos2 ô + sin2 o = 1\n\n(2) tan â\n\nsin a\n\ncos a\n\nDémonstration ABC est un triangle rectangle en A et ô = ABC\n\n(1) cos2â+sin2a = f^'\n\n\\dL/\n\n2 'AC]2 _ AB2 , AC2\n\nBC2 BC2\n\ncos2 a + sin2 a =\n\nAB2 +AC2\n\nBC2\n\nOr, d'après l'égalité de Pythagore AB2 + AC2 = BC2.\n\nBC2\n\nBC2\n\n= 1.\n\nDonc cos2 a + sin2 a =\n\nAC\n\n212\n\nUtilisation\n\n• La formule (1 ) permet de calculer cos â connaissant sin â (ou sin â connaissant cos â).\n\n• La formule (2) permet de calculer cos o, sin o ou tan a connaissant deux de ces nombres.\n\nTICE Savoir-faire\n\nir\n\nUtiliser les touches cos , sin , tan\n\nde la calculatrice\n\nC-Asro\n\n©©o©^\n\nCéVi-rtSO*\n\na. Déterminer la valeur approchée par défaut au centième près de 2,7 x cos 11\n\nb. Déterminer la valeur approchée par défaut au millième près de sin 74°.\n\nc. o désigne un angle aigu d'un triangle rectangle et tan ^ ^ -\n\nDéterminer la valeur approchée par excès au degré près de la mesure de o.\n\nAvec Casio fx-92 Collège 2D+\n\nSi le symbole O n'apparaît pas en haut de l'écran, on procède aux réglages:\n\nSt(.1*1 lit MUOfcllWlMU\n\na. 2,70© 11 ©\n\nDonc 2,7 x cos 11° = 2,65.\n\nb. \"E* 74©\n\nDonc sin 74° = 0,961.\n\nStLWTIb frctan F\n\nc # > 70'3©\n\nDonc ô =67°.\n\n3 (Deg)\n\n2, 7*ci;IS ( 11\n\n2*650393395\n\nsiriC74\n\n0?9612616959\n\nhretanC7-3\n\n66,80140949\n\nLi\n\nAvec Tl-Collège Plus\n\nSi le symbole deg n'apparaît pas en haut de l'écran, on procède aux réglages\n\nmil (mettre DEG en surbrillance)\n\nlïick-\n\na. 2,7©' C® 11 ©\n\nDonc 2,7 x cos 11° = 2,65.\n\nb. 74\n\nDonc sin 74° = 0,961.\n\nbim&L\n\nc. #©7®3©\n\nDonc a ~ 67°.\n\nHa\n\n2,?-cos ai\n\n2 j 6503*?3355\n\nMa\n\nsinC74\n\n0,961261656\n\nH3\n\narc t.sn >'7:3\n\n66.80140949\n\nâ Avec la calculatrice, donner l'arrondi au centième\n\nde:\n\na. 1,2 x sin 13'\n\n. sin 51\n\nb. 4 : tan 24°\n\ne. (tan 25°) x 5\n\nc. cos 3^\n\nS a désigne un angle aigu d'un triangle rectangle.\n\nAvec la calculatrice, donner l'arrondi au degré de la\n\nmesure de o lorsque:\n\n- 1\n\na. cos a = -^\n\nb. sin â = 0,748\n\nc- tan o = —\n\nCHAPITRE 11 «Triangles rectangles.Trigonométrie 213\n\nCalculer des longueurs\n\na. ABC est le triangle rectangle ci-dessous.\n\nCalculer AC, puis donner son arrondi au\n\nmillimètre.\n\n6 cm\n\nb. EFG est le triangle rectangle ci-dessous.\n\nCalculer GF, puis donner son arrondi au\n\ncentimètre.\n\n49\n\na. Dans le triangle ABC rectangle en A:\n\nAC ... . .... AC\n\nsin ABC =\n\nc'est-à-dire sin 28° =\n\nDonc AC = 6 x sin 28°.\n\nAvec la calculatrice, on trouve AC « 2,8 cm.\n\nb. Dans le triangle EFG rectangle en G :\n\n1,2\n\ntan EFG = 1^- c'est-à-dire tan 49° =\n\nFG\"\n\n1,2\n\nFG\n\nDonc FG x tan 49° = 1,2 et FG= .r.0.\n\ntan 49\n\nAvec la calculatrice, on trouve FG « 1,04 m.\n\nOn connaît un angle, l'Hypoténuse\n\net on cherche le côté Opposé.\n\nSOHCAHTOA\n\nOn utilise le Sinus.\n\nOn connaît un angle, le côté Opposé\n\net on cherche le côté Adjacent.\n\nSOHCAHTOA\n\nOn utilise la Tangente.\n\nJ'applique : exercices 7 à 9\n\nDéterminer des angles\n\nAvec les données indiquées sur la figure ci-contre,\n\ndéterminer les arrondis au degré des mesures\n\ndes angles LJK et LKJ .\n\nCTi\n\n• Dans le triangle JKL rectangle en L:\n\ncos LJK = c'est-à-dire cos LJK = .\n\nJK 6\n\nAvec la calculatrice, on trouve LJK ~ 61°.\n\n• Les angles aigus d'un triangle rectangle sont\n\ncomplémentaires, donc:\n\nLKJ = 90° - LJK\n\nAinsi LKJ ~ 90° - 61° c'est-à-dire ljd-290.\n\nOn cherche un angle dont\n\non connaît le côté Adjacent\n\net l'Hypoténuse.\n\nSOHCAHTOA\n\n1 Y\n\nOn utilise le Cosinus.\n\nAvec la calculatrice, il est inutile\n\nd'effectuer auparavant 2,9 : 6.\n\nArccos (2^9^-6\n\n61*09666546\n\nJ'applique : exercices 10 et 11\n\n214\n\nUtiliser les formules de trigonométrie\n\nîntcrectîve\n\na désigne un angle aigu d'un triangle rectangle. On sait que cos o = 0,6.\n\nCalculer les valeurs exactes de sîn a, puis de tan o.\n\n• On sait que cos2 o + sin2 o = 1, donc:\n\n0/62 + sin25=1\n\nsin2 0 = -}- 0,62 =1 - 0,36 = 0,64.\n\nPuisque sinâ > 0, on en déduit que:\n\nsin a - V0,64 c'est-à-dire sin â = 0,8.\n\n^ - smc? ,\n\n• On sait que tan a = , donc:\n\ncos o\n\nXar\\à=^- = ^ c'est-à-dire tan â\n\n0,6 6\n\nOn remplace cos o par 0,6.\n\nIl existe deux nombres dont\n\nle carré est 0,64, à savoir:\n\n0,8 et - 0,8.\n\nIci, on conserve seulement 0,8\n\nqui est positif.\n\n= 4 ✓ I 0,8 _ 8xi^r_ 8\n\n0,6 6xivr 6\n\nJ'applique : exercice 12\n\no1\n\nT.\n\n7 Une famille souhaite\n\ninstaller un toboggan\n\ndans son jardin. La\n\ndescente a une longueur\n\nde 3 m et forme un angle\n\nde 40° avec le sol.\n\nQuelle est la hauteur h de ce toboggan ?\n\nDonner l'arrondi au cm.\n\nKAP est un triangle rectangle en A tel que:\n\nKP = 8,6 cm et KPA = 35°.\n\na. Calculer la longueur KA, puis donner son arrondi au mm.\n\nb. Calculer une valeur approchée de AP.\n\nAxel : « Le périmètre de ce triangle est strictement infé-\n\nrieur à 18 cm ».\n\nManon : « Tu as tort, son périmètre est strictement supé-\n\nrieur à 18 cm ».\n\nQu'en pensez-vous?\n\n10 RST est un triangle rectangle en R tel que :\n\nRS = 7,2 cm et RT = 5,1 cm.\n\nDéterminer les arrondis au degré des mesures des\n\nangles RST et RTS.\n\n11 Monsieur Duchêne veut barder (recouvrir) de bois\n\nle pignon nord de son atelier.\n\nOn donne : AD = 6 m, AB = 2,20 m, SM = 1,80 m.\n\nM est le milieu de [BC].\n\n//-\n\nPignon nord de l'atelier\n\nIl a besoin de connaître la mesure de l'angle SBM pour\n\neffectuer certaines découpes.\n\nDéterminer la mesure de l'angle SBM. On arrondira le\n\nrésultat au degré près.\n\n18 a désigne un angle aigu d'un triangle rectangle.\n\nOn sait que sin o = 0,28.\n\nCalculer les valeurs exactes de cos o et de tan o.\n\nCHAPITRE 11 -Triangles rectangles.Trigonométrie 215\n\nSavoir-faire ATELIER BREVET\n\nPenser aux instruments de géométrie\n\n^pro.ÏÏI:TCT31 Pour passer l'épreuve de mathématiques, il faut penser à apporter son matériel de\n\ngéométrie car certains exercices demandent de construire une figure en vraie grandeur.\n\nLe soin apporté à cette construction est pris en compte dans le barème.\n\n13 m ht L ■ i [■ T=m dnb\n\nL'unité de longueur est le centimètre.\n\nABCD est un carré tel que AB = 4.\n\nLe point M est situé dans le carré ABCD et vérifie AM = 2,4 et DM = 3,2.\n\nLa droite (AM) coupe la demi-droite [DC) au point I.\n\n1. Faire une figure en vraie grandeur.\n\n2. Montrer que le triangle AMD est rectangle en M.\n\n3. Calculer au degré près la mesure de l'angle DAM.\n\n4. Dans le triangle ADI rectangle en D, exprimer tan (DAI).\n\nEn déduire une valeur approchée au mm près de la longueur DI.\n\n1. Bien lire l'énoncé : le point M est à l'intérieur du carré ABCD. Pour placer le point M, penser\n\nà utiliser le compas.\n\n2. Penser à l'égalité de Pythagore.\n\n3. Ici, on peut utiliser aussi bien le cosinus, que le sinus ou la tangente.\n\n4. Il revient au même de noter tan(DAI) ou tan DAI.\n\nComprendre une formule nouvelle\n\nIl peut arriver que certains sujets proposent une formule qui n'a jamais été étudiée en\n\nclasse. Ne pas s'affoler. Observer la formule, repérer les opérations, et comprendre le rôle joué par\n\nchaque nombre qui intervient.\n\n14 D'après DNB\n\nLa formule d'AI-Kashi permet de calculer le troisième côté d'un triangle connais-\n\nsant deux côtés et un angle. Pour un triangle ABC, on a :\n\nBC2 = AB2 -h AC2 - 2AC x AB x cos (BAC ).\n\nOn considère pour tout l'exercice que :\n\nAB = 6 cm, AC = 12 cm et BAC = 60°.\n\n1. Construire un triangle ABC vérifiant les conditions précédentes.\n\n2. Donner la valeur de cos (BAC).\n\nEn déduire avec la formule d'AI-Kashi que l'on a BC2 = AC2 + AB2 - AC x AB.\n\nMontrer que BC2=108.\n\n3. En déduire que le triangle ABC est rectangle en B.\n\nAl-Kashi est\n\nun mathématicien\n\net astronome perse\n\n(1380; 1429).\n\nfcl'Jl»]:* 1. Il peut être utile de faire d'abord au brouillon une figure à main levée. Mais sur la copie, il\n\nfaut utiliser la règle graduée et le rapporteur.\n\n2. Utiliser la calculatrice pour donner la valeur exacte de cos BAC.\n\n3. Penser à l'égalité de Pythagore.\n\n216\n\nRéponses p, 311\n\nTriangle rectangle\n\n(S DRG est un triangle rectangle en R, R\n\n1. Dans chaque cas, indiquer\n\nle mot à écrire à la place des\n\npointillés.\n\na. [DG] estT... du triangle rectangle DRG.\n\nb. Pour l'angle GDRf [GR] est le côté ... et [DR] est le\n\ncôté\n\n2. Indiquer les segments à écrire à la place des poin-\n\ntillés : l'angle RQD a ... pour côté adjacent et... pour\n\ncôté opposé.\n\nDans le triangle PLM rectangle en L,\n\nquel segment:\n\na, est l'hypoténuse?\n\nb, est le côté adjacent à l'angle PML?\n\nc, est le côté opposé à l'angle MPI ?\n\nCosinus, sinus, tangente\n\nd'un angle aigu\n\nDans le triangle OUI rectangle en y\n\nO, donner l'expression de:\n\na. cos OUI b, sin OUI C. tan OUI\n\nCD Que représente chaque quotient\n\npour l'angle OVL du triangle VOL\n\nci-contre?\n\na. vo\n\nVL\n\nb. PL\n\nOV\n\nPL\n\nVL\n\nCD ABC est un triangle rectangle en B\n\ntel que AB = 3 dm et BC = 4 dm,\n\n1. Calculer la longueur AC.\n\n2. Donner la valeur décimale de:\n\na. cos ACB b. sin ACB c. tan ACB\n\nG31. Pourquoi le triangle PGR ci-dessous est-il\n\nrectangle?\n\n<0\n\np\n\n13 cm\n\n2. Donner sous forme de fraction irréductible la valeur de:\n\na. cosGPR b. sinGPR c. tanGPR\n\nES À l'aide de points nommés de la\n\nfigure, exprimer de deux façons diffé-\n\nrentes:\n\na. cos BAC b, sin BAC c. tan BAC\n\n03 Dans chaque cas, on veut calculer la longueur\n\ndu segment rouge. Dire s'il est préférable d'utiliser le\n\ncosinus, le sinus ou la tangente de l'angle aigu donné,\n\na. /v b,\n\nv-\n\n7,2 cm\n\nDans chaque cas, une seule réponse est exacte.\n\nLaquelle ?\n\nT. A partir de l'égalité sin40° = on peut écrire:\n\na. AB =\n\n510 40'\n\nb. AB = 5 x sin 40° c. AB = sin 40°\n\n_ 8\n\n2. A partir de l'égalité ta 0 25°= , on peut écrire;\n\na. EF= tan25 b. EF = 8xtan25'' c. EF =\n\ntar\\25a\n\nDans chaque cas, expliquer comment on peut\n\ncalculer la longueur AB.\n\na. » b.\n\nS c 0}\n\n57\n\nDans chaque cas, expliquer comment on peut\n\ndéterminer la mesure de l'angle ÂBC.\n\na. b.\n\n14 cm\n\nCN\n\n3 cm\n\nDeux formules de trigonométrie\n\nm Dans un triangle rectangle en C, on sait que\n\ncosÀBC = 0,8.\n\na. Calculer (sin ABC)2 et en déduire sin ABC.\n\nb. Calculer tan ABC.\n\n£[3 a désigne un angle aigu d'un triangle rectangle.\n\n- 8 15\n\nOn sait que cosâ = — et sinâ = —-\n\nExprimer tan â avec une fraction.\n\nCHAPITRE 11 -Triangles rectangles.Trigonométrie 217\n\nTriangle rectangle\n\n1^11. Dans le triangle ABC rectangle en B, quel\n\nsegment est:\n\na. Thypoténuse?\n\nb. le côté adjacent à l'angle BAC ?\n\nc. le côté opposé à l'angle BCÂ ?\n\n2. Dans le triangle BHC rectangle en\n\nH, quel angle a pour côté opposé :\n\na. [BH] ? b. [CH] ?\n\ngSL»\n\nConstruire un triangle DEF tel que:\n\nEF = 4,3 cm, DEF =29° et EFD = 610.\n\nQuelle est la nature de ce triangle? Expliquer.\n\nKy MNP est un triangle rectangle en M tel que:\n\nMNP = 45°^\n\na. Calculer la mesure de l'angle MPN.\n\nb. Que peut-on en déduire pour le triangle MNP ?\n\nes AEL est un triangle rectangle en A tel que :\n\nAE = 2,4 cm et AL = 7 cm.\n\na. Calculer la longueur du côté [EL].\n\nb. Quel est le centre du cercle circonscrit à ce triangle?\n\nQuel est son rayon ? Expliquer.\n\nA 5,7 cm j\n\nS)\n\nVD\n\nr\\\n\nS '7\n\nAvec les données de la\n\nfigure,\n\na. expliquer pourquoi le triangle\n\nATU est rectangle;\n\nb. calculer la longueur AO, arrondie\n\nau mm.\n\n([{^Tracer un cercle dont un diamètre [AB] mesure\n\n6 cm, puis placer un point F sur le cercle tel que :\n\nBAF =56^\n\nCalculer la mesure de l'angle ABF. Expliquer.\n\nCosinus, sinus, tangente\n\nd9un angle aigu\n\nTBI est le triangle rectangle ci-dessous\n\nRecopier et compléter.\n\n• L'hypoténuse est\n\n• Le côté adjacent à l'angle TBI est\n\n• Le côté opposé à l'angle TBI est....\n\nDonc cosTBI = —,\n\nsin TBI =\n\net tan TBI =\n\nRecopier et compléter.\n\nDans le triangle DOR rectangle en O:\n\na. sin RDO = — b. cos... = ^\n\n• • •\n\nOD\n\nC.... DRO =\n\nOR\n\nDR\n\nd-... RDO =\n\nOD\n\nIjJUtOC est un triangle rectangle en Ttel que:\n\nTC = 6 cm et OC = 7,5 cm.\n\na. Calculer la longueur TO.\n\nb. En déduire les valeurs exactes de cos TOC, sin TOC et\n\ntan tOC (donner les réponses sous forme de fractions\n\nirréductibles).\n\nWrid trois triangles rectangles.\n\nK I\n\nDire dans lequel de ces triangles on a :\n\na. sin IJK = IK\n\nIJ\n\nb. tan JIK = JK\n\nIJ\n\nc. cos IJK = il\n\nJK\n\nPour les exercices 38 à 41, construire, si possible,\n\nun triangle rectangle ABC donc l'angle ABC vérifie\n\nl'égalité indiquée.\n\n03 cos ABC = ;|\n\nCD sin ABC =\n\nsin ABC = ^\n\ntan ABC - 3\n\nADN est le triangle rectangle ci-dessous.\n\n35° N\n\n1. a. Que représente le côté [AD] pour l'angle AND ?\n\nb. Calculer la longueur DA et donner son arrondi au cm.\n\n2. a. Que représente le côté [ND] pour l'angle AND ?\n\nb. Calculer la longueur ND, puis donner son arrondi\n\nau cm.\n\n(23 VEN est le triangle rectangle ci-dessous.\n\n5,8 cm\n\na. Calculer la longueur VE et donner son arrondi au mm.\n\nb. Calculer une valeur approchée de EN.\n\n218\n\no* S\n\nABC est le triangle rectangle ci-contre.\n\na. Calculer la longueur AC, puis B\n\ndonner son arrondi au cm.\n\nb. Donner l'arrondi au dixième de\n\nm2 de l'aire du triangle ABC.\n\na. Construire un triangle MTV rectangle en M tel\n\nque:\n\nMV = 2,8 cm et TVM = 63°.\n\nb. Calculer la longueur VT, puis donner sa valeur appro-\n\nchée par excès au dixième près.\n\nc. Calculer une valeur approchée du périmètre du\n\ntriangle MTV.\n\nSur la figure codée ci-dessous, les droites (GD) et\n\n(AJ) se coupent en N.\n\ncm\n\n7 cm\n\na. Pourquoi a-t-on DNJ = ANG ?\n\nb. Exprimer sin DNJ et sin ANG.\n\nr • DJ 2\n\nc. Expliquer pourquoi -y- = ^ .\n\nd. En déduire la longueur DJ.\n\na. Construire un triangle JKL rectangle en Ktel que:\n\n11 = 8,2 cm et JK = 4,7cm.\n\nb. Que représente [JK] pour l'angle KLJ ?\n\nc. Déterminer l'arrondi au degré de la mesure de l'angle\n\nKLJ.\n\nd. En déduire l'arrondi au degré de la mesure de l'angle\n\nKJL.\n\nCEI Porter un regard critique Dans le débat ci-dessous, qui\n\na raison? Argumenter.\n\nNiky : « Avec ma calculatrice, je trouve r\n\nque l'angle IMR mesure à peu près\n\n44° ».\n\nAlexis : « Inutile I on voit bien que MIR\n\nest un triangle isocèle, donc l'angle\n\nIMR mesure 45°».\n\n(£] Maths in english\n\nWith the data provided on the\n\nfigure opposite, détermine the\n\nvalues, rounded off to the nearest\n\ndegree, of the measurements of ^^ j\n\nthe angles RST and STR. ^ 5,6 cm\n\n7,2 cm\n\nm Un funiculaire permet de\n\nmonter au sommet de la butte Mont-\n\nmartre à Paris. D'une longueur de\n\n108 m, la voie a un angle d'élévation\n\nde 19,5° par rapport à l'horizontale.\n\nDéterminer une valeur approchée\n\nau mètre près de la différence d'altitude entre la gare\n\nd'arrivée et la gare de départ.\n\niOv\n\nï ^Vilî\n\nConnaître le Monde\n\nLa tour Burj Khalifa, la plus haute du\n\nmonde, a été inaugurée en 2010, à\n\nDubaï (Émirats Arabes Unis).\n\nUne personne de 1,65 m, située\n\nà 100 m de la tour, mesure\n\nHOP = 83,10 (O représente son œil).\n\nCalculer l'arrondi au mètre de la\n\nhauteur de cette tour.\n\n100 m\n\nTania fait voler son cerf-\n\nvolant. La ficelle a une longueur\n\nTC de 40 m.\n\na. La ficelle est tendue et le cerf-\n\nvolant est à 35 m du sol. Calculer\n\nl'arrondi au degré de la mesure de l'angle STC.\n\nb. Porter un regard critique Tania affirme: « Mon cerf-volant\n\nserait deux fois moins haut si l'angle STC était deux fois\n\nplus petit ».\n\nQu'en pensez-vous?\n\n03 Un arbre a été cassé lors\n\nd'une tempête. Un forestier a\n\npris des mesures:\n\n- distance entre le pied de\n\nl'arbre et sa cime: PC = 4,5 m;\n\n- mesure de l'angle entre le\n\nsol et l'arbre :ICP =25°.\n\nCalculer l'arrondi au dm de la hauteur de l'arbre avant\n\nla tempête.\n\nDeux formules de trigonométrie\n\nl>£j Dans un triangle ABC rectangle en A, on sait que:\n\nsin ÂCB = 0,936.\n\na. Calculer (cos ACB)2 et en déduire la valeur exacte de\n\ncos ACB.\n\nb. En déduire l'arrondi au millième de tan ACB.\n\nCEI Dans un triangle MNP rectangle en M, on sait que :\n\ncos MNP =\n\nCalculer les valeurs exactes de sin MNP et tan MNP.\n\nCHAPITRE 11 -Triangles rectangles.Trigonométrie 219\n\nest un angle aigu d'un triangle rectangle tel que: I rm Cette figure n'est pas à l'échelle.\n\n35 - 12\n\ntano = — et cosa = ^y-\n\nCalculer la valeur exacte de sin a de deux façons diffé-\n\nrentes.\n\njj^^Ttacer un cercle de centre 0 et de diamètre AB = 6 cm.\n\nM est un point de ce cercle tel que BM = 4,8 cm.\n\nDéterminer la mesure arrondie au degré de l'angle BAM.\n\nCEI SOI est un triangle isocèle en O tel que :\n\nÔSI = 58° et IS = 6,5 cm.\n\nCalculer son aire, puis arrondir au mm2.\n\nUn charpentier doit réaliser la charpente schéma-\n\ntisée ci-dessous pour\n\nlaquelle AJ = 3,1 m et A ^ ,<?,\n\nJD = 5,4 m.\n\nCalculer les arrondis au\n\ndixième des mesures\n\ndes angles BAD et\n\nCDA, ainsi que des\n\nlongueurs AD et BC.\n\n<0\n\nW.,\n\n(BC) // (AD)\n\nUn métier Charpentier\n\nLe charpentier bois réalise\n\nen atelier les pièces desti-\n\nnées à l'ossature du toit\n\npuis les assemble et les\n\nmonte sur le chantier.\n\nCe métier physique se\n\npratique souvent en équipe et à l'extérieur.\n\nPlusieurs niveaux de formation : CAP, Bac Pro ou Bac\n\nSTI2D ou BP, BTS (bac + 2).\n\nhttp://www.omsep.fr/Decouvrîr-les-metîers\n\n15 m\n\n:c\n\n53\n\n\"N\n\nThalamège\n\nQuelle est la hauteur du mât de ce bateau ?\n\nOn donnera la valeur approchée par excès au dm près.\n\nai ou faux ?\n\nPour les exercices 61 à 66, dire si l'affirmation est\n\nLe cosinus et le sinus d'un angle aigu sont des\n\nnombres compris entre 0 et 1.\n\nlîEI La tangente d'un angle aigu est un nombre\n\ncompris entre 0 et 1.\n\nE3 ô est un angle aigu d'un triangle rectangle.\n\nAlors: coso = sin(900-o).\n\nUS Dans le triangle VOF ci-contre,\n\non peut écrire VO =\n\nO 5,9 cm\n\n49\n\ntan 49° '\n\nfEI Dans le triangle VOF ci-contre,\n\non peut écrire VF = 5,9 x cos 410.\n\nË3jlp est un triangle tel que:\n\nJL = 23,5 cm, JP = 12,5 cm et JLP = 28°.\n\nCe triangle est rectangle en J.\n\nCalcul meiital et réfléchi\n\nLongueurs inconnues\n\nABC est un triangle rectangle en A.\n\nCalculer mentalement:\n\na. AB lorsque BC = 7 cm et sin ACB = 0,4 ;\n\nb. AC lorsque AB = 8 cm et tan ABC = 0,5 ;\n\nc. BC lorsque AB = 3,2 cm et cos ABC = 0,4.\n\nlîEI Mesures d'angles inconnues A\n\nOn donne: tan32°~ 0,625;\n\ntan 45° = 1 ; tan 58° - 1,6. ^\n\nAvec les données ci-dessus, déter- 8 cm B\n\nminer mentalement les arrondis au degré des mesures\n\ndes angles ACB et BAC.\n\n220\n\n|^| Améliorer la rédaction\n\nÉnoncé. ABC est un triangle\n\nrectangle en B tel que AC = 7 cm\n\net BAC = 21°.\n\nCalculer l'arrondi au mm de BC.\n\n7 cm\n\nVoici la copie de Lorine. En tenant compte des remarques\n\ndu professeur, réécrire correctement la solution.\n\nDans le taangle ABCj isui BAC =1^.^011.1\n\nUtiLisatan die La tagonomeW ^ '\n\na Justifier I I\n\ndigne sin£vl0 =\n\nJ rédaction a revoir\n\nJuste I I 1,1 I\n\nParticiper à un débat\n\nOn considère les trois triangles ci-dessous.\n\nC F\n\n58°\n\n32,\n\n(N\n\n^ 4,4 cm\n\nDylan : « On peut utiliser la trigonométrie dans ces trois\n\ntriangles ».\n\nLucie: « Non, pas dans le triangle DEF».\n\nLéo: « Pas du tout! On ne peut utiliser la trigonométrie\n\ndans aucun de ces triangles».\n\nQui a raison dans le débat ci-dessus ? Expliquer.\n\nChoisir une méthode\n\nÉnoncé. SEP est un triangle\n\nrectangle en E tel que SE = 2,9 cm\n\net EP = 3,7 cm.\n\nCalculer l'arrondi au degré de la\n\nmesure de l'angle ESP.\n\nen\n\nfN J\n\nE 3,7 cm\n\nLilian: «Je vais utiliser l'égalité de Pythagore pour\n\ncalculer SP. Ensuite, j'utiliserai le cosinus de ESP ».\n\nJulia : « Tu n'as pas besoin de calculer SP ! On peut déter-\n\nminer la mesure de ESP directement».\n\nRédiger la solution en suivant la méthode de Julia.\n\nArgumenter\n\na est un angle aigu d'un triangle rectangle.\n\nFélix:« Aveccos2â + sin25 = 1 ettanâ =\n\ns\\r\\o\n\ndémontrer que 1 + tan2 o =\n\nComment fait-il?\n\ncoso\n\n,je peux\n\n»-\n\ncosz o\n\nÉviter une erreur\n\nÉlise doit calculer l'arrondi au mm\n\nde CA dans le triangle CAL ci-contre.\n\nVoici un extrait de sa copie:\n\n3,1 cm\n\nsmiT0 = donc ÇA =\n\nr r r f ^\n\nd'où.\n\nW>II- ,â\n\nsin<27-3?1\n\nOp 9339609555\n\nPour expliquer sa réponse. Élise\n\nmontre l'écran de sa calculatrice.\n\nSa calculatrice est bien en mode\n\ndegré mais le résultat obtenu n'est pas correct.\n\na. Quelle erreur Élise a-t-elle commise?\n\nb. À quoi correspond le résultat affiché?\n\nc. Quelle séquence de touches Élise aurait-elle dû taper?\n\nDonner deux possibilités.\n\nAvec les données de la figure ci-dessous, Cyril devait\n\ncalculer la longueur AD.\n\nA >\n\nVoici la fin de ce qu'il\n\n40°/ a écrit:\n\nat> - 4 x ton lo0\n\nCM (,0°\n\nA-t-il raison? Expliquer.\n\nI^J Narration de recherche\n\nJuliette parie qu'elle peut D\n\ntraverser la rivière repré-\n\nsentée ci-contre en moins de\n\n2 minutes.",
  "metadata": {
    "source": "fomesoutra",
    "pdfFile": "t_l_charger_20_62_mb.pdf",
    "year": null,
    "zone": null,
    "hasCorrection": true
  }
}