{
  "sourceType": "livre",
  "subject": "mathematiques",
  "grade": "3eme",
  "chapter": null,
  "title": "t l charger 4 89 mb - part 2",
  "content": "2) Soit MPN un triangle tel que : MN =\n\nW ; NP = 6 et MP= 6,5.\n\nMontrer que ce triangle est rectangle en N. (1pt)\n\n3) Une parcelle de forme carrée a une superficie comprise strictement\n\nentre 4oom2 et 900m2.\n\nDéterminer un encadrement du coté de cette parcelle. (1pt)\n\n4) Soit (O,\u0016,\r\u000e \u0017\u000e\u0018 un repère orthonormé du plan d’unité graphique 1 cm.\n\nConstruire la droite (D) d’équation x− 2y + 1 = 0. (0,5pt)\n\n43\n\n5) On considère la fonction rationnelle q définie sur IR\\ { −\n\nW } par :\n\nq(x) =\n\n\u001a-\u0003ƒ¯\u0002Œ\n\nW\u001a\u0002®\n\nCalculer l’image de −2 par q. (0,5pt)\n\n6) ) Dans le plan muni d’un repère orthonormé, la droite (D) a pour\n\ncoefficient directeur m=\n\n¬ et la droite \u0014D′\u0018 a pour coefficient\n\nm’= −\n\n® .\n\nJustifier que ces deux droites sont perpendiculaires. (1pt)\n\n7) Lors d’une course de vitesse au 100 mètres plat en EPS (Education\n\nPhysique et Sportive), le professeur a relevé le temps mis (en secondes)\n\npar un groupe d’élèves : 14 ; 16,5 ; 15,5 ; 13 ; 12 ; 15,6 ; 11,8 ; 13,2 ;\n\n14,4. Calculer la moyenne de cette série statistique. (1pt)\n\n8) Soit IJK un triangle tel que ±²O\n\n³ = 75°. &\r\u000e est un vecteur non nul. On\n\ndésigne par I’J’K’ l’image du triangle IJK par la translation de vecteur\n\n&\r\u000e . Sans construire les deux triangles, quelle est la mesure de l’angle ±+´+O+\n\n‹ ?\n\nJustifier la réponse. (1pt)\n\n9) Soit h une application affine de IR dans IR et décroissante. Comparer\n\nh (−3) et h(−7). (1pt)\n\n10) Dans la figure suivante, le triangle OAB est rectangle en O.\n\nSachant que tan K\n\n‹= √ƒ\n\nƒ .\n\nCalculer la distance OB.(1pt)\n\n44\n\n11) Dans la figure suivante, les droites (AB) et (HP) sont parallèles.\n\nCompléter les égalités suivantes :\n\n¶\n\n¶• =\n\n…..\n\n….. =\n\n….\n\n…. (1pt)\n\nDeuxième partie : (10 points)\n\nDans cette partie, I et II sont indépendantes.\n\nI. (4 points)\n\nUn ouvrier a travaillé pendant 30 jours au total sur deux sites d’orpaillage.\n\nSur le premier site, il gagnait 5.000F par jour et sur le second site, il était\n\npayé à 6.000F par jour. Il a gagné au total 160.000F sur les deux sites.\n\n1)\n\nEn désignant par x le nombre de jours de travail sur le premier site\n\net par y le nombre de jours de travail sur le second site, traduire les données\n\ndu problème par un système d’équations. (2 pts)\n\n2) Déterminer le nombre de jours de travail sur chaque site. (2pts)\n\n45\n\nII. (6points)\n\nOn considère la fonction f définie de IR vers IR par\n\nf (x)= (3x-2)2 – 4(x2 -5x +1)\n\n1) Développer, réduire et ordonner f(x). (1pt)\n\n2) Résoudre dans IR l’équation f(x)=0. (1pt)\n\n3) On pose g(x) =\n\n®¯-\u0002¸¯\n\n¯\u0014W\u0003¯\u0018\n\na) Déterminer l’ensemble de définition Dg de g. (1pt)\n\nb) Simplifier g(x) sur l’ensemble de définition de g. (0,5 pt)\n\nc) Déterminer l’antécédent de 3 par g. (1pt)\n\nd) Résoudre dans IR, l’inéquation g(x) ≥ 0. (1,5pt)\n\n46\n\nEXAMEN DU B.E.P.C. BURKINA FASO\n\nSESSION DE 2014\n\nUnité-Progrès-Justice\n\nEPREUVE DE MATHEMATIQUES (Ier tour)\n\n(Calculatrices non autorisées)\n\nDurée : 2 heures\n\nCoefficient : 05\n\nL’épreuve comporte deux (2) parties indépendantes à traiter\n\nobligatoirement.\n\nPremière partie : (10 points)\n\nDans cette partie, toutes les questions sont indépendantes.\n\n1. f est une application polynôme définie dans IR par\n\nf(x) = 8\u0005W−18− (2x+3)2\n\na) Développer, réduire et ordonner f(x) (1pt)\n\nb) Factoriser f(x) (1pt)\n\n2. Sachant que 2,345<x<2,346 et −7,3<y<−7,2, encadrer x+y (0,5pt)\n\n3. Résoudre dans IR x IR par la méthode d’identification le système\n\nsuivant :\n\n¹\n\n( =\n\nƒ −4\n\n3\u0005 + 2( −14 = 0\n\n(1,5pt)\n\n4. Dans un repère cartésien (K, ı,\r\u000e ȷ\u0018\r\r\u000e, on donne\n\n47\n\n&\r\u000e = 3\u0016\u000e −\n\n¬ \u0017\u000e, \u0012\u000e '\n\n¼½\n\nŒ ) et ¾\r\r\u000e = &\r\u000e + \u0012\u000e\n\nCalculer les coordonnées du vecteur ¾\r\r\u000e (0,5pt)\n\n5. Soit g une application affine telle que g(x) =\n\n\u0003¬\n\nƒ x+\n\nReprésenter graphiquement l’application g dans le plan muni d’un\n\nrepère orthonormal (K, \u0016,\r\u000e \u0017\u000e \u0018, unité graphique 1 cm. (1pt)\n\n6. Soit l’inéquation 3x−4y<\n\nW.\n\nParmi les couples de réels suivants, deux couples sont solutions de cette\n\ninéquation :\n\na) (0 ; −3) ; b) (2 ;5) ; c) (\n\nW ; 1\u0018 ; d) (4 ;−3) ; e) (−1 ;4)\n\nRecopier seulement les lettres des bonnes réponses. (1pt)\n\n7. Soit h l’application définie par h(x)=|−2\u0005 + 1| + 5\u0005.\n\nMontrer que h est une application affine par intervalles. (1pt)\n\n8. Dans la figure suivante, les droites (AE) et (CD) se coupent en I.\n\nDémontrer que les droites (AD) et (CE)\n\nsont parallèles. (1pt)\n\n48\n\n9. (D) est la droite d’équation 3x−4y−1=0\n\nDéterminer le coefficient directeur de (D). (0,5pt)\n\n10. Dans le repère cartésien (O, \u0016\u000e, \u0017\u000e\u0018, on donne les points A (−3 ;\n\n\u0003®\n\nW \u0018 et M\n\n(2 ; −1)\n\nCalculer les coordonnées du point A’ symétrique de A par rapport à M.\n\n(1pt)\n\nDeuxième partie : (10 points)\n\nDans cette partie, I et II sont indépendants.\n\nI. Soit h une fonction rationnelle telle que h(x) =\n\n\u001a-\u0003W\u001a\u0002Œ\n\n\u0014Œ\u0003\u001a\u0018\u0014®\u001a\u0003¬\u0018\n\n1) Déterminer l’ensemble de définition D h de h . (0,5pt)\n\n2) Justifier que sur D h, h(x)=\n\nŒ\u0003\u001a\n\n®\u001a\u0003¬ (0,5pt)\n\n3) Calculer si possible l’image de chacun des réels −2 et\n\n® (1pt)\n\n4) Calculer h (`2\u0018 (on rendra entier le dénominateur de h (`2\u0018 (1pt)\n\n5) Résoudre dans D h :\n\na. L’équation h(x) = 3 (0,5pt)\n\nb. L’inéquation h (x) ≤ 0 (1,5pt)\n\nII. Dans le plan muni d’un repére orthonormal \u0014K, \u0016\u000e, \u0017\u000e\u0018, unité graphique\n\n1 cm , on donne les points A(3,−1) ; B(−1,2) ; C(2,6) .\n\n1. Placer les points A ,B et C dans le repère. (0,75pt)\n\n2. Calculer les distances AB,BC et AC . En déduire la nature du\n\ntriangle ABC. (2pts)\n\n49\n\n3. Soit \u0014\u000f\u0018 le cercle circonscrit au triangle ABC de centre M et de\n\nrayon r. (1pt)\n\na. Tracer \u0014\u000f\u0018 (0,25pt)\n\nb. Calculer les coordonnées de M et le rayon r . (1pt)\n\n4. Soit (T) la tangente à \u0014\u000f\u0018 en A.\n\nDeterminer une équation cartésienne de (T) (1pt)\n\n50\n\nEXAMEN DU B.E.P.C. BURKINA FASO\n\nSESSION DE 2013 Unité-Progrès-Justice\n\nEPREUVE DE MATHEMATIQUES (Ier tour)\n\n(Calculatrices non autorisées)\n\nDurée : 2 heures\n\nCoefficient :\n\nL'épreuve comporte deux (2) parties indépendantes à traiter\n\nobligatoirement.\n\nPremière partie: (12 points)\n\nDans cette partie, toutes les questions sont indépendantes.\n\n1. Ecrire seulement la ou les lettres du ou des couples qui vérifient\n\nl'inéquation suivante :2x + 3y > 6 a. (1 ; 2) ; b. (2 ; 0) ; c. (0 ; 2) ;\n\nd. (2 ; 1) (1 pt)\n\n2. Soit f le polynôme tel que f(x) = 3x2 + 2\u0005√3 + 1\n\nFactoriser f(x) en utilisant l'identité remarquable qui convient. (1 pt)\n\n3. Soit g le polynôme tel que g (x) = (x - 1)2 + 3(x+3) (x - 1) - (x - 2)\n\n(x - 1).\n\nFactoriser g (x). (1,5 pt)\n\n4. Dans un repère orthonormé (o, \u0016\u000e, \u0017\u000e ) du plan, résoudre graphiquement\n\ndans IR x IR le système suivant : \u0014Q\u0018 À2\u0005 + ( = 5\n\n\u0005 −3( = 6 \u00143,5D:?\u0018\n\n51\n\n5. Soit h une application affine telle que : ℎ\u0014\u0005\u0018 = G1 −√2J\u0005 +\n\nDonner le sens de variation de h. (1,5pt)\n\n6. Soient a et b deux réels tels que = 3√5 8: \b = 2√11. Comparer a et\n\nb. (1,5 pt)\n\n7. Soit ABC un triangle rectangle en B tel que AB = 6, BC = 8, AC = 1\n\nO. Sans faire une figure,\n\na. Calculer le sinus de l'angle BÂC. (1pt)\n\nb. Trouver la mesure de l'angle BÂC à un degré près (1° près) par excès.\n\n(1pt)\n\nOn donne :\n\nSinus\n\n0,7880\n\n0,7986\n\n0,8090\n\n0,8192\n\n0,8290\n\nAngle\n\n52°\n\n53°\n\n54°\n\n55°\n\n56°\n\n52\n\nDeuxième partie : (08 points)\n\nDans cette partie I et II sont indépendantes\n\nI/ Soit la figure suivante : (Le candidat ne reproduira pas la figure)\n\nOn donne : OE = 4 ; OEF est un triangle équilatéral.\n\n1. Trouver, en justifiant la réponse, la mesure de l’angle QR\u000f\n\n‹et celle de\n\nl’angle\fR\u000f\n\n‹. (2pts)\n\n2. Montrer que ABC est un triangle rectangle. (On précisera le sommet\n\nde l’angle droit). (1pt)\n\n3. Justifier que la longueur du segment P\u000b\u000fS est égale à 4√3.(1pt)\n\nOn donne sin 30° =\n\nW ; cos 30° = √ƒ\n\nW et tan 30° = √ƒ\n\n.\n\n4. Déterminer la longueur du segment [BC]. (1pt)\n\nII/ A l'occasion du succès de son fils à l'examen du BEPC, un père veut\n\norganiser une fête. Il décide d'acheter des poulets et des pintades. Il\n\nsouhaite avoir plus de 12 volailles.\n\n53\n\n1. En désignant par x le nombre de pintades et y celui des poulets,\n\ntraduire cette situation par une inéquation. (0,5pt)\n\n2. Le père voudrait dépenser moins de 45000F pour l'achat des volailles.\n\nSachant qu'une pintade coûte 2500F et un poulet 3000F, trouver une\n\ninéquation qui traduit cette situation. (0,5 pt)\n\n3. a) A partir des questions précédentes, montrer que l'on obtient le\n\nsystème suivant :\n\nÀ \u0005 + ( > 12\n\n5\u0005 −6( < 90\n\n\u00140,5D:?\u0018\n\nb. Combien de poulets le père peut-il obtenir s'il veut 6 pintades ?\n\nDonner toutes les possibilités. (1,5 pt)\n\n54\n\nEXAMEN DU B.E.P.C. BURKINA FASO\n\nSESSION DE 2012 Unité-Progrès-Justice\n\nEPREUVE DE MATHEMATIQUES (Ier tour)\n\n(Calculatrices non autorisées) Durée : 2 heures\n\nCoefficient : 05\n\nPremière Partie : (12 points)\n\nDans cette partie, toutes les questions sont indépendantes.\n\nI)\n\nRecopier seulement le numéro de la question et la lettre de la\n\nbonne réponse.\n\n1. E = 2-5x-3 (2x+1) s’écrit simplement :\n\na. E = -11x-1 b. E= -30x-1 c. E=-11x+5 d. E=-11x+3 (0,5pt)\n\nb. Soit l’inéquation x +\n\nW <\n\nÂ\n\nL’ensemble des solutions de cette inéquation est :\n\na.Ã\n\nƒ ; +∞Å b.Ã−∞;\n\nƒÅ c.Ã−∞;\n\nƒÅ d.Ã\n\nƒ ; +∞Å (0,5pt)\n\nRésoudre dans IR x IR, en utilisant la méthode des combinaisons\n\nlinéaires, le système\n\nd’ équations suivant : À3\u0005 −( = −1\n\n2\u0005 + 3( = 5 (1,5pt)\n\nII)\n\nSoit f l’application linéaire définie par f(-6) = 3\n\nDéterminer l’expression f(x) = ax de cette application\n\nlinéaire. (0,5pt)\n\n55\n\nIV) Soit la figure suivante :\n\nOn donne : sin 30°=\n\nW ; cos 30°= √ƒ\n\nW ; tan 30°=\n\n√ƒ\n\n1. Calculer la distance BC. (1pt)\n\n2. Calculer la distance AD. (1pt)\n\nV) 1. Montrer que \u0014√3 −1\u0018W= 4−2√3 (0,5pt)\n\n2. Donner une écriture simplifiée de A= `4 −2√3 sous la\n\nforme a +b. où a et b sont des entiers relatifs.(0,5pt)\n\nVI) AÔB est un angle de 65°. A’Ô’B’ est l’image de AÔB par la\n\ntranslation de vecteur K\n\nSans construire la figure, donner en justifiant la réponse, la\n\nmesure de A’Ô’B’. (1pt)\n\n56\n\nVII) La figure ci-dessous représente un cône, avec O’A’= 12 ; OS=\n\n36 ; SO’= 21,6 ;\n\n(O’A’)// (OA).\n\nSans reproduire la figure, calculer la distance OA. (1pt)\n\nVIII) Soit la fonction rationnelle f définie de IR par f(x) =\n\n\u0003\u001a\u0002Œ\n\nW\u001a\n\nCalculer l’image de √5 par f. (On donnera le résultat avec un\n\ndénominateur entier.) (0,5pt)\n\nIX) Dans le plan muni d’un repère orthonormal (O, \u0016\r\r\u000e, \u0017\u000e), on\n\ndonne\n\n\u000e =\n\n4\u0016\u000e −3\u0017\n\n\u000f\u0013\n\n\u000e = −\u0016\u000e +\n\n¬ \u0017\u000e\n\nSans faire la figure,\n\n1. Montrez que les droites (AB) et (CD) sont parallèles.\n\n2. Sachant que KL\n\n\u000e= -2\u000f\u0013\n\n\u000e, calculer les coordonnées du vecteurKL\n\n\u000e.\n\nX) Dans le plan muni d’un repère orthonormal (O, \u0016\r\r\u000e, \u0017\u000e) (unité : 1cm),\n\n1 Représenter la droite (D1) : y = −\n\nWx+3. (0,5pt)\n\n2. Déterminer une équation de la droite (D2) perpendiculaire à\n\n(D1) et passant par l’origine du repère. (1pt)\n\n57\n\nEPREUVE N°6 : BEPC 2016 (2nd tour)\n\nPremière partie : (10 points)\n\nDans cette partie, toutes les questions sont indépendantes.\n\n1) Simplifier l’écriture du nombre réel A= \u0019√¿\u0003W\n\n√ƒ \u001e \u0019√¿\u0002W\n\n√ƒ \u001e. (1 pt)\n\n2) Factoriser en utilisant l’identité remarquable qui convient, D\u0014\u0005\u0018 =\n\n3\u0005W −4\u0005√3 + 4. (1 pt)\n\n3) Résoudre dans IR l’équation 5\u0014\u0005 −2\u0018 −\u0005\u0014\u0005 −2\u0018 = 0 (1 pt)\n\n4) Soit la fonction rationnelle q définie sur IR\\Æ−\n\nƒÇ par «\u0014\u0005\u0018 =\n\nŒ\u0003W\u001a\n\nƒ\u001a\u0002Œ.\n\nCalculer l’image de −\n\nW par\n\nq. (1 pt)\n\n5) £ étant une application affine croissante, comparer\n\n£\u0014−È\u0018 8: £\u0014−3\u0018. (1 pt)\n\n6) ABC est un triangle rectangle en B, O est un point du plan et\n\nA’B’C’ est l’image de ABC par la symétrie\n\nde centre O. Justifier que les droites (A’B’) et (B’C’) sont perpendiculaires\n\n(la figure n’est pas demandée). (1 pt)\n\n7) IJK est un triangle rectangle en I. Sans construire la figure,\n\ncalculer la longueur de [IJ] sachant\n\nque IK=3cm ; IOÉJ=60°.\n\nOn donne sin60°=\n\n√ƒ\n\nW , cos60°=\n\nW , tan60°=√3. (1 pt)\n\n8) Dans le plan muni d’un repère cartésien (O,\u0016,\r\u000e \u0017\u000e), on donne le\n\nvecteur\n\n\u000e '\u0003ƒ\n\nÊ\n\n) et le point\n\n58\n\nB (5 ; -4). Calculer les coordonnées du point A. (1 pt)\n\n9) Le plan est muni d’un repère (O,\u0016,\r\u000e \u0017\u000e). Sans construire le repère,\n\ndéterminer une équation de\n\nla droite (∆) passant par A(-3 ;2) et de vecteur directeur &\r\u000eG\u0003®\n\nƒ J\n\n. (1 pt)\n\n10) Soient (D1) et (D2) les droites d’équations (D1) : −3\u0005 + 2( −\n\n5 = 0 et\n\n(D2) : 3\u0005 −2( −4 = 0. Sans construire ces droites, montrer\n\nqu’elles sont parallèles. (1 pt)\n\nDeuxième partie : (10 points)\n\nExercice 1 (3 points)\n\nUne entreprise de la place a dix employés répartis en deux catégories : une\n\ncatégorie A et une catégorie B. Les employés de la catégorie A travaillent\n\nchacun à 7000 francs par jour et ceux de la catégorie B à 3000 francs par\n\njour. L’entreprise paye au total 58000 francs à l’ensemble des employés à\n\nla fin de la journée.\n\n1) En désignant par x le nombre d’employés de la catégorie A et par y celui\n\ndes employés de la catégorie B, traduire l’énoncé sous la forme d’un\n\nsystème d’équations. (1 pt)\n\n2) Déterminer le nombre d’employés de chaque catégorie. (2 pts)\n\n59\n\nExercice 2 (2 points)\n\nLes notes obtenues par des candidats à l’issue d’un test de recrutement\n\npour complément d’effectif dans un lycée ont été réparties selon le\n\ntableau ci-dessous.\n\nNotes\n\n[0 ;5[\n\n[5 ;10[\n\n[10 ;15[\n\n[15 ;20[\n\nEffectif\n\n10\n\n20\n\n8\n\n1) Calculer la moyenne des notes de cette série statistique. (1 pt)\n\n2) Construire l’histogramme des effectifs de cette série statistique. (1 pt)\n\nEchelle : À \u00058 F8? \b?9@??8?: 19A DE&; 5 DE@B:?.\n\n\u00058 F8? E;FEBBé8?: 19A DE&; 4 é7è\u00128?.\n\nExercice 3 (5 points)\n\nDans le plan muni d’un repère orthonormal (O,\u0016,\r\u000e \u0017\u000e), unité graphique 1\n\ncm, on donne A(1 ;1), B(3 ;0), C(7 ;-2) et D(2 ;3).\n\n1) Placer les points A, B, C et D. (1 pt)\n\n2) Montrer que les points A, B et C sont alignés. (1 pt)\n\n3) On donne \u000b\f = √5 , \u000b\u000f = 3√5 , \u000b\u0013 = √5 8: \f\u0013 = √10.\n\nMontrer que le triangle isocèle ABD est aussi un triangle\n\nrectangle. (1 pt)\n\n4) Soit (∆) la droite parallèle à (BD) et passant par C.\n\na) Construire (∆). (0.5 pt)\n\nb) En utilisant le théorème de Thalès, calculer la distance CE où E\n\nest le point d’intersection des\n\ndroites (∆) et (AD). (1.5 pt)\n\n60\n\nEPREUVE N°7 : BEPC 2018\n\nPREMIERE PARTIE : (10 points)\n\nDans cette partie toutes les questions sont indépendantes.\n\nI) Pour chacune des questions ci-dessous, écrire le numéro de la question\n\nsuivi de la lettre correspondant à la bonne réponse.\n\n1) Parmi les couples de réels suivants, un seul est solution de l’inéquation\n\n\u0005 + 2( −3 < 0. Lequel ?\n\na) (3 ;0) ; b(1 ;4) ; c(-1 ;\n\nW) ; d(1 ;-2) (1 pt)\n\n2) Le développement de £\u0014\u0005\u0018 = \u0019\n\nW + 3\u0005\u001e2 est :\n\na)\n\n¬+9x2 ; b)\n\n¬ −9\u00052 ; c)\n\n¬ −3\u0005 + 9x2 ; d) 9x2+3x+\n\n¬ (1 pt)\n\n3) FGT est un triangle rectangle en F tel que FG=8 ; FT=6 et GT=10\n\ntan©œ vaut :\n\n\u0018\n\n® ; b)\n\n® ; c)\n\n¬ ; d)\n\nƒ (1 pt)\n\n4) Soit la droite (D) d’équation ( = \u0005√2 +\n\nW et la droite (∆) d’équation\n\n( = A\u0005 + 2.\n\nPour quelle valeur de m, (D) et (∆) sont-elles parallèles ?\n\na)−√2 ; b)\n\n√W ; c)\n\nW ; d) 1 (1 pt)\n\n61\n\n5) Les deux cônes de rayon KA et IB sont opposés par le sommet. Les\n\ndroites (BI) et (KA) sont parallèles.\n\nKA=4.2cm ; KS=6cm ; SI=4cm. La valeur de BI en cm est :\n\na) 2.8 ; b) 2 ; c) 1.5 ; d) 5. (1 pt)\n\nII. 1) Dans chacun des cas suivants, représenter sur une droite graduée\n\nl’ensemble des réels x tels que :\n\na) \u0005 ∈S1; 4P ; \b\u0018 \u0005 ∈S −∞; −3S. Hachurer les parties non convenables. (1\n\npt)\n\n2) Résoudre dans IRXIR par la méthode d’identification le système :\n\nÀ 4\u0005 −( = 9\n\n3\u0005 + 2( = 4 (1 pt)\n\n62\n\n3) Dans le plan muni d’un repère orthonormal (O,\u0016,\r\u000e \u0017\u0018,\n\n\u000eon donne A(2 ;-3)\n\net B(-1 ;5).\n\nDéterminer un vecteur directeur de la droite passant par A et B. (1 pt)\n\n4) Le tableau ci-dessous indique la répartition (en%) des accidents de la\n\nroute selon les heures de la journée.\n\nTranche\n\nhoraire\n\n[0 ;4[\n\n[4 ;8[\n\n[8 ;12[\n\n[12 ;16[\n\n[16 ;20[\n\n[20 ;24[\n\n5%\n\n11%\n\n14%\n\n20%\n\n35%\n\n15%\n\ncumulée\n\ncroissante\n\na) Reproduire le tableau en le complétant. (0.75 pt)\n\nb) Quelle est la classe modale ? (0.25 pt)\n\n5) On considère la figure suivante dans laquelle les points E, A et C sont\n\nalignés ; les points F, A et B sont alignés. AF=12cm ; AC=5cm ;\n\nAB=7.5cm et AE=8cm.\n\nLa figure n’est pas en dimension réelle et n’est pas à reproduire.\n\nMontrer que (BC) et (EF) sont parallèles. (1 pt)\n\n63\n\nDEUXIEME PARTIE : (10 points)\n\nDans cette partie, I et II sont indépendantes.\n\nI. Dans le plan muni d’un repère orthonormal (O,\u0016,\r\u000e \u0017\u0018,\n\n\u000e (unité graphique :\n\n1cm) placer les points A(3 ;-1) ; B(2 ;3) et C(-2 ;2).\n\n1) Calculer les distances AB ; AC et BC. (0.75 pt)\n\n2) Démontrer que le triangle ABC est rectangle et isocèle. (1 pt)\n\n3) Calculer les coordonnées du point D image de C par la translation de\n\nvecteur\n\n\u000e. (1 pt)\n\n4) a) Déterminer une équation de la droite passant par les points B et C. (1\n\npt)\n\nb) Déterminer une équation de la droite (∆) passant par A et parallèle à\n\nla droite (BC). (1 pt)\n\n5) Dans le même repère, résoudre graphiquement le système\n\nÀ−\u0005 + 4( −10 ≤10\n\n−\u0005 + 4( + 7 ≥0\n\nHachurer les parties non solutions. (1 pt)\n\nII. Soient £\u0014\u0005\u0018 = \u0005W −9 + \u0014\u0005 + 3\u0018\u00141 −4\u0005\u00188: §\u0014\u0005\u0018 = \u00142\u0005 −1\u0018\u00143\u0005 + 2\u0018.\n\n1) Factoriser f(x). (1 pt)\n\n2) Résoudre dans IR l’équation : g(x)=0. (0.5 pt)\n\n3) On donne : «\u0014\u0005\u0018 =\n\n\u0014\u001a\u0002ƒ\u0018\u0014\u0003ƒ\u001a\u0003W\u0018\n\n\u0014ƒ\u001a\u0002W\u0018\u0014W\u001a\u0003Œ\u0018\n\na) Déterminer l’ensemble de définition Dq de q. (0.5 pt)\n\nb) Montrer que «\u0014\u0005\u0018 =\n\n\u001a\u0002ƒ\n\n\u0003W\u001a\u0002Œ sur Dq. (1 pt)\n\n4) Quel est l’antécédent de\n\nƒ par q ? (0.5 pt)\n\n64\n\n5) Epreuve N°8 : BEPC 2019, premier tour\n\nPremière partie (10 points)\n\nI Pour chacune des questions ci-dessous, écrire le numéro de la question\n\nsuivi de la lettre correspondant à la bonne réponse\n\n1) Parmi les couples de réels suivants, un seul est solution du\n\nsystème :\n\nÀ5\u0005 −3( = 0\n\n\u0005 + ( = 0 .Lequel ? a) (11 ;13) ; b) (8 ;16) ; c) (9 ;15) ; d) (10 ;14).\n\n(0,5 pt)\n\n2) (C) est un cercle de centre A et de rayon r=4 et (D) une droite du\n\nplan. La distance du point A à la droite (D) est égale à 3. La droite\n\n(D) coupe le cercle (C) en :\n\na) Un point ; b) deux points ; c) trois points ; d) aucun point. (0,5\n\npt)\n\n3) ABCDFGHE est un cube. I, J, K et M sont les milieux respectifs\n\nde [AB], [BC], [CD] et [GH].\n\nParmi les triangles suivants, lequel est rectangle ? (0,5 pt)\n\na) AJH ; b) BKH ; c) IDA ; d) AKH\n\n65\n\nII\n\n1) Résoudre dans IR, l’équation\n\nƒ\u001a\u0003®\n\nW =\n\n¬\u0003\u001a\n\n(1 pt)\n\n2) Dans le plan muni d’un repère orthonormal (O,\u0016\u000e,\u0017\u000e), on donne les\n\npoints M(-1 ;3) et P(-4 ;-2). Calculer la distance MP. (1pt)\n\n3) Soit f la fonction rationnelle définie par f(x)=\n\nƒ\u001a-\u0003¬\n\n\u0014Œ\u0002\u001a\u0018\u0014W\u001a\u0003ƒ\u0018.\n\nDéterminer l’ensemble de définition Df de la fonction f. (1pt)\n\n4) Soit [MN] un segment de longueur 9cm. En utilisant le théorème\n\nde Thalès, construire le point A sur [MN] tel que MA=\n\n¬MN.\n\n(1pt)\n\n5) Le triangle BEP est rectangle en E tel que BE=4 ; EP=2 et\n\nBP=2√5\n\nCalculer sin BaœE. (1pt)\n\n6) Soit APQ un triangle d’aire 14cm2, O un point quelconque du\n\nplan. On note A’P’Q’ l’image du triangle APQ par la symétrie de\n\ncentre O. Sans faire la figure, justifier que l’aire du triangle\n\nA’P’Q’ est 14cm2. (1pt)\n\n7) Soit A=3√12 −2√75 −4√3. . Ecrire A sous la forme a√\b où a∈ Z\n\net b∈IN. (1pt)\n\n8) Dans le plan muni d’un repère orthonormal (O,\u0016\u000e,\u0017\u000e), on donne les\n\ndroites (D) : 4x+y-1=0 et (D’) : y=\n\n¬ x-\n\n®. Justifier que (D) et (D’)\n\nsont perpendiculaires. (1pt)\n\n66\n\n9) La figure ci-dessous est la représentation graphique d’une\n\napplication linéaire f dans le plan muni d’un repère orthonormal\n\n(O,\u0016\u000e,\u0017\u000e), unité 1cm.\n\nDéterminer l’expression de f(x) pour tout réel x. (1 pt)\n\nDeuxième partie (10 points)\n\nI (5points)\n\nUne étude statistique sur la durée de vie de lampes électriques a\n\npermis d’établir l’histogramme suivant\n\n67\n\n1) Reproduire et compléter le tableau suivant : (3,5 pts)\n\nDurée de\n\nvie\n\n[0 ;10[\n\n[10 ;20[\n\n[20 ;30[\n\n[30 ;40[\n\n[40 ;50[\n\nEffectif\n\ncumulée\n\ncroissante\n\nCentres des\n\nclasses\n\n2) Quelle est la classe modale ? (0,5 pt)\n\n3) En utilisant les centres des classes, calculer la durée de vie\n\nmoyenne d’une lampe. (1 pt)\n\nII\n\nLe plan est muni d’un repère orthonormal (O,\u0016\u000e,\u0017\u000e), unité graphique\n\n1cm. On donne les points A(1 ;2) ; B(-2 ;0) et C(4 ;0).\n\n1)\n\na) Placer les points A, B et C. (0,75 pt)\n\nb) Déterminer une équation cartésienne de la droite (∆) passant\n\npar les points A et B. (1 pt)\n\nc) En utilisant l’équation de la droite (∆), vérifier que E(4 ;4) est\n\nun point de la droite (∆). (1pt)\n\n2) On note C’ le symétrique de C par rapport au point A. Placer le point\n\nC’ puis calculer ses coordonnées. (1,25 pts)\n\n3) Démontrer que les vecteurs \u000fQ\n\n\u000e et \u000f\n\n\u000e sont orthogonaux.\n\n68\n\nEpreuve N° 9\n\nPremière partie (10 points)\n\nI) Ecrire le numéro de la question suivi de la lettre correspondant à la\n\nbonne réponse.\n\n1) On donne x=-1 et y=−√3 . Le résultat du calcul x-2y+√3 est :\n\na) -1-√3 b) 1+3√3 c) -1-3√3 d) -1+3√3. (0,5 pt)\n\n2) Parmi les couples de réels suivants, lequel est solution de\n\nl’inéquation : -2x+3y≤\n\n?\n\na) (0 ;1) ; b) (0 ;\n\nW ) ; c) (1 ;2) ; d) (-2 ;0). (0,5 pt)\n\n3) Soit l’application linéaire g définie par g(x)= (È -3,14)x ;\n\nL’application g est :\n\na) Constante ; b) croissante ; c) décroissante ; d) nulle. (0 ;5 pt)\n\nII)\n\n1) Dans le plan muni d’un repère orthonormal (O,\u0016\u000e,\u0017\u000e), on donne\n\nA(4 ;2) et C(\n\nW ;4).\n\nCalculer AC. (1 pt)\n\n2) D, L et R sont trois points d’une droite graduée d’abscisses\n\nrespectives x ; -1 et 2.\n\nExprimer en fonction de x, la distance DL+LR. (1,5 pts)\n\n3) ABC est un triangle tels que AB=5, BC=\n\n®√®\n\nW et AC=\n\nW.\n\nMontrer que ABC est un triangle rectangle. (1 pt)\n\n69\n\n4) MNP est un triangle rectangle en N, de hauteur {NH]. On donne\n\nMH= 7 et HP= 9.\n\nCalculer NH. (1 pt)\n\n5) Soit le polynôme h défini dans IR par ℎ\u0014\u0005\u0018 = \u00147\u0005 + 1\u0018\u00143\u0005 −2\u0018 −\n\n9\u0005W + 4.\n\nEcrire h(x) sous forme d’un produit de deux facteurs du premier degré. (1\n\npt)\n\n6) X et y sont deux nombres réels tels que 3< x<\n\nŒ®\n\nW et\n\nƒ <y<\n\n®.\n\nA quel intervalle appartient le produit \u0005( ? (1 pt)\n\n7) Dans la figure ci-dessous, A, P et E sont des points du cercle de\n\ncentre O.\n\nOn donne AaœE=75° et PKœE=90°. Déterminer la mesure de l’angle P\u000bšE.\n\n(1 pt)\n\n8) CAP est un triangle rectangle en A. On donne CP= 15, AC=9 et\n\nAP=12.\n\nCalculer tan AaœC. (1pt)\n\n70\n\nDeuxième partie (10 points)\n\nI (5points)\n\nOn considère la fonction rationnelle K définie par k(x)=\n\n\u0014\u0003W\u001a\u0002ƒ\u0018\u0014\u001a\u0003®\u0018\n\n¬\u001a-\u0003Ð\n\n.\n\n1) Montrer que 4\u0005W −9 = \u0014−2\u0005 + 3\u0018\u0014−2\u0005 −3\u0018. (0,5 pt)\n\n2) Déterminer l’ensemble de définition Dk de k. (0,5 pt)\n\n3) Pour tout x Є Dk, montrer que k(x)=\n\n\u0003\u001a\u0002®\n\nW\u001a\u0002ƒ . (0,5 pt)\n\n4) a) Déterminer l’image du réel -2 par k. (1 pt)\n\nb) Déterminer l’antécédent du réel 3 par k. (1 pt)\n\n5) Résoudre dans IR, l’inéquation k(x)≤ 0. (1,5 pts)\n\nII (5points)\n\nLe plan est muni d’un repère orthonormal (O,\u0016\u000e,\u0017\u000e), d’unité graphique\n\n1cm.\n\n1) Tracer dans ce repère la droite (∆) : x-2y+1=0 (1 pt)\n\n2) Soit A (3 ;1). Déterminer une équation cartésienne de la droite (D)\n\npassant par A et parallèle à (∆).\n\n(1 pt)\n\n3) Soit B (-2 ; y). Déterminer y pour que B appartienne à la droite\n\n(D). (1 pt)\n\n4) Soit (C) le cercle de diamètre [AB].\n\na) Calculer le rayon R de ce cercle. (1 pt)\n\nb) Déterminer les coordonnées du point E, centre de ce cercle.\n\n(1pt)\n\n71\n\nEpreuve N°10\n\nPremière partie (10 points)\n\nI Ecrire le numéro de la question suivi de la lettre correspondant à la bonne\n\nréponse.\n\n1) Le système À2\u0005 −3( = −1\n\n−4\u0005 + 6( = 2 admet dans IR X IR :\n\na) Un couple solution ; b) aucun couple solution ; c) une infinité\n\nde couples solutions ; d) F8&\u0005 9E&D78? ?E7&:@EB? \u00140,5 D:\u0018\n\n2) Le résultat du calcul\n\nƒ-\n\nƒX\n\nW est :\n\na) Nul ; b) un décimal négatif ; c) un nombre rationnel ; d) un\n\nentier\n\n3) X est un nombre réel tels que x›-1 et 3≥x. Le réel x appartient à\n\nl’intervalle :\n\na) [-1 ;3] ; b) [-1 ;3[; c)] -1 ;3[; d)] -1 ;3].\n\nII\n\n1) Soit le nombre réel A=√®Ò\u0003√Œ¸\u0002 √WÒÒ\n\n√¸\u0003√W\n\n. Montrer que A est un entier\n\nnaturel. (1 pt)\n\n2) Dans un repère orthonormal (O,\u0016\u000e,\u0017\u000e), on considère les vecteurs &\r\u000e et\n\n\u0012\u000e tels que\n\n&\r\u000e =\n\n® \u0016\u000e-3\u0017\u000e et \u0012\u000e=\n\n\u0003Â\n\n¬ ±\u000e+\n\nŒÒ \u0016\u000e. Montrer que &\r\u000e et \u0012\u000e sont colinéaires. (1pt)\n\n3) I et J sont deux intervalles de IR tels que I=]−∞ ;3] et\n\nJ=] -1 ;10]. Représenter sur une droite graduée, l’intervalle I∩J. (1pt)\n\n72\n\n4) Pousbila et M’baboanga, deux élèves du CE2 ont des crayons de\n\ncouleurs. Pousbila dit à M’baboanga : « Si tu me prends un crayon\n\nde couleur, j’aurai le même nombre de crayons de couleurs que toi.\n\nMais, si je te prends un crayon de couleur, j’aurai deux fois le\n\nnombre de crayons de couleurs qui te reste. » En désignant par x le\n\nnombre de crayons de couleurs que possède Pousbila et par y le\n\nnombre de crayons de couleurs que possède M’baboanga, traduire\n\npar un système de deux équations du premier degré à deux\n\ninconnues les propos de Pousbila. (2pts)\n\n5) Dans un repère orthonormal (O,\u0016\u000e,\u0017\u000e), on donne : A(-1 ;2) ; B(0 ;1) et\n\nC(-3 ;4). Montrer que les points A, B et C sont alignés. (1,5pts)\n\n6) On considère le polynôme P défini dans IR par : P(x)= (5x-6)(-\n\n1+2x)+(2x-3)2. Développer, réduire puis ordonner P(x) suivant les\n\npuissances croissantes de x. (1pt)\n\n7) SABCD est une pyramide de sommet S et de base, le rectangle\n\nABCD. On donne : AB=4cm ; AD=3cm et AS= 7cm. Calculer AC.\n\n(1pt)\n\n73\n\nDeuxième partie(10points)\n\nI Soit la figure suivante où (C) est un cercle de centre O et de diamètre\n\n[AC].\n\n1) Déterminer la mesure de l’angle \u000f\fQ\n\n‹ puis celle de l’angle \u000bQ\n\n‹.\n\n(2pts)\n\n2) Montrer que le triangle ABC est rectangle. (1pt)\n\n3) On donne OE= 4 et BC= 4√3 . Calculer la longueur du segment\n\n[AB]. (1pt)\n\nII Soit g, l’application numérique définie par g(x)= I-2x+3I-1.\n\n1) Montrer que g est une application affine par intervalles. (1pt)\n\n2) Représenter l’application g dans un repère orthonormal (O,\u0016\u000e, \u0017\r\u000e),\n\nd’unité graphique 1cm. (1pt)\n\n74\n\nIII Une société d’électricité propose à ses clients deux systèmes de\n\nfacturation mensuelle.\n\nSystème 1 : Le client paye une prime fixe de 2500F et 90F pour chaque\n\nKWh consommé.\n\nSystème 2 : Le client paye uniquement 95F pour chaque Kwh consommé.\n\nSoient x, le nombre de Kwh consommés ; h, l’application qui donne le\n\nmontant à payer dans le système1 et k, l’application qui donne le montant\n\nà payer dans le système 2.\n\n1) Exprimer h(x) et k(x) en fonction de x. (2pts)\n\n2) Si un client consomme 200 Kwh dans le mois, dans quel système paye-\n\nt-il le montant le moins élevé ? (1pt)\n\n3) Pour quelle valeur de x un client paye le même montant dans les deux\n\nsystèmes ? (1pt)\n\n75\n\nCORRIGES\n\nCORRIGES\n\n76\n\nCORRIGES DES EPREUVES DE MATHEMATIQUES\n\nEXAMEN DU BEPC BURKINA FASO\n\nSESSION DE 2017 Unité-Progrès-justice\n\nPROPOSITION DE CORRIGE DE L’EPREUVE DE\n\nMATHEMATIQUES (1er tour)\n\nPremière Partie : (10 points)\n\n1) £\u0014\u0005\u0018 = 4\u0005ƒ + 5\u0005¬ + 3 −2\u0005\n\n= 4\u0005ƒ + 5\u0005¬ −2\u0005 + 3 \u00140,5D:\u0018\n\n2) §\u0014\u0005\u0018 = |−3\u0005 + 6|\n\n|−3\u0005 + 6| = −3\u0005 + 6 ?@ −3\u0005 + 6 ≥0 ; \u0005 ≤2\n\n|−3\u0005 + 6| = −\u0014−3\u0005 + 6\u0018?@ −3\u0005 + 6 ≥0 ; \u0005 ≤2\n\n§\u0014\u0005\u0018 = −3\u0005 + 6 ?@ \u0005S−∞; 2S (1pt)\n\n3) La mesure de l’angle \f\u000b\u000f\n\n‹ est 34° car deux angles inscrits",
  "metadata": {
    "source": "fomesoutra",
    "pdfFile": "t_l_charger_4_89_mb.pdf",
    "year": null,
    "zone": null,
    "hasCorrection": true
  }
}