{
  "sourceType": "livre",
  "subject": "mathematiques",
  "grade": "3eme",
  "chapter": null,
  "title": "t l charger 270 kb - part 3",
  "content": "2°) Déterminer la hauteur AB et la distance OA. (02 points)\n\n3°) Faire la construction de l’image d’un objet MN de hauteur 2cm donnée par une lentille divergente\n\nde distance focale 1,5cm sachant que la distance OM = 4cm. (01 point)\n\nBONNE CHANCE !\n\n29\n\nEXAMEN DE BFEM BLANC (durée 2H) (Coef :2)\n\nEPREUVE DE PHYSIQUE-CHIMIE\n\nExercice 1 (4pts)\n\nUne solution d’hydroxyde de sodium de 500mL est obtenue en dissolvant 20g de NaOH dans de\n\nl’eau.\n\n1) Quelles sont les concentrations de cette solution ? (1pt)\n\n2) Sur 10mL de cette solution, on verse quelques gouttes de BBT. Quelle est la teinte prise par la\n\nsolution ? (0,5pt)\n\n3) On dose ces 10mL par une solution d’acide chlorhydrique (HCl).\n\na) Quelle est la couleur de la solution au point équivalent ? (0,75pt)\n\nb) Quels sont le nombre de moles et la masse d’acide nécessaire à ce dosage ? (1pt)\n\nc) Quel serait la teinte de la solution si on dépasse le point équivalent ? (0,75pt)\n\nExercice 2 (5pts)\n\n1- Equilibrer les équations suivantes :\n\na- Fe2O3 + Al Al3O4 + Fe (0,5pt)\n\nb- Al + HCl AlCl3 + H2 (0,5pt)\n\nc- C4H10 + O2 CO2 + H2O (0,5pt)\n\n2- La réduction à chaud de l’oxyde ferrique (Fe2O3) se produit selon l’équation ci-dessous :\n\nFe2O3 + H2 Fe + H2O\n\na- Equilibrer cette équation. (0,5pt)\n\nb- Calculer la masse de fer obtenue par réduction de 160g d’oxyde ferrique. (1pt)\n\nc- Le fer ainsi produit est attaqué par de l’acide chlorhydrique (HCl) dilué en excès et à froid.\n\nc 1- Ecrire l’équation bilan de la réaction entre l’acide et fer. (1pt)\n\nc 2- En déduire la masse de dihydrogène recueillie. (1pt)\n\nDonnées nécessaires: M (Na)=23g/mol ; M (O)=16g/mol ; M (H)=1g/mol ; M (Cl)=35,5g/mol ;\n\nM(Fe) = 56g/mol.\n\nExercice 3 (5pts)\n\nUn objet AB de taille 10cm est placé devant une lentille convergente de vergence 10 δ.\n\n1- Calculer la distance focale de la lentille. (1pt)\n\n2- Construire à l’échelle 1/5, l’image A’B’ de AB et donner ses caractéristiques dans les deux\n\ncas\n\na- AB est placé à 15cm devant le centre optique de la lentille. (2pts)\n\nb- AB est placé à 5cm devant le centre optique de la lentille. (2pts)\n\nExercice 4 (6pts)\n\nUne bille de masse m=25kg se déplace sur le trajet ABCDE sous l’action de son poids et d’une force\n\nmotrice F d’intensité 10N toujours parallèle au déplacement. On donne AB=25m ; BC=15m ;\n\nCD=25m ; DE=10m ; h=15m et g=10N/kg.\n\n1) Arrivée en D, la bille atteint le sol en E sous l’action de son poids seul. Comment appelle-t-on\n\nce mouvement ? (1pt)\n\n2) Calculer le travail du poids sur chaque portion de trajet et en déduire le travail total du poids\n\nde A à E. (1,5pts)\n\n3) Calculer le travail du poids si la bille à partir de A atteint le sol en O. Que peut-on en\n\nconclure ? (1,5pt)\n\n30\n\n4) Calculer la puissance développée par la force F s’il lui a fallu 1mn05s pour parvenir la bille\n\njusqu’en D avec une vitesse constante V. Trouver la valeur de cette vitesse.\n\n(2pt)\n\nA B\n\nh C\n\nD\n\nO\n\nE (Sol)",
  "metadata": {
    "source": "fomesoutra",
    "pdfFile": "t_l_charger_270_kb.pdf",
    "year": 2005,
    "zone": null,
    "hasCorrection": true
  }
}