{
  "sourceType": "annale",
  "subject": "Français",
  "grade": "3eme",
  "chapter": null,
  "title": "t l charger download",
  "content": "BEPC BLANC\n\nSESSION 2026\n\nCOMPOSITION FRANÇAISE\n\nCete epreuve comporte deux (02) pages\n\nCette epreuve comporte deux sujet. Le candidat traitera l'un des sujets au choix.\n\nPrenier sujet : Texte argumentatif (sujet de réflexion)\n\nAu cours d'un débat radioditlusé portant sur I'éducation à la citoyenneté, un auditeur\n\naffime ceci:«Le manque de civisme observé chez certains individus est nuisible au bon\n\nfonctionnement de la société. »\n\n1)\n\nldentifie le thènne abordé dans ce sujet. (2 pts)\n\n2) Reformule la thèse de l'auditeur. (4 pts)\n\nCoefficient: 2\n\nDurée\n\n:\n\n2 Heures\n\n3) Rédige ta production pour étayer le point de vue de I'auditeur. (14 pts)\n\nDeuxiènme sujet: ILe résumé de texte argumentatif\n\nL'Intelligence Artificielle\n\nL'Intelligence Artificielle (IA) est aujourd'bui au Coeur de nombreuses innovations\n\ndans presque tous les domaines d'activité. L'un des aspects importants de l'intelligence\n\nArtificielle est sa capacité à exécuter les tâches que nous lui donnons à faire automatiquement.\n\nElle est capable de produire de nombreuses choses en seulement quelques secondes.\n\nCette intelligence numérique est révolutionnaire car elle contribute å I'apprentissage et\n\nau développement cognitif chez l'être humain.. Elle permet aux machines d'exécuter des tâches\n\nqui étaient autrefois réservées aux humains, comme la reconnaissance vocale, I'analyse de\n\ndonnées et la prise de décisions.\n\nL'Intelligence Artificielle (lA) représente une avancée majeure. Dans le domaine de la\n\nsanté, elle améliore le diagnostic et la recherche médicale. Dans I'éducation et la formation,\n\nelle personnalise I'apprentissage en s'adaptant aux besoins des élèves et des étudiants. Dans les\n\ntransports, elle favorise la mise en place de véhicules autonomes, réduisant ainsi le nombre des\n\naccidents causés par des erreurs humaines sur les routes, et qui endeuillent de nombreuses\n\nfamilles chaque année.\n\nCependant, cette lechnologie comporte aussi des risques. En effet, elle pourrait\n\nremplacer de nombreux emplois dans le monde. Ce qui entrainerait inévitablement une hausse\n\ndu chômage dans certains secleurs. De plus. elle soulève la question de l'éthique: les machines\n\npeuvent-eles prendre des décisions sans supervision humaine ? Enfin, la collecte massive de\n\ndonnées par les entreprises d'intelligence artificielle pose des problėmes de confidentialité, de\n\nprotection et de sécurité des informations personnelles.\n\nEn conclusion, le déploiement de I'Intelligence Artificielle dans la société laisse\n\nentrevoir à la fois des usages positifs, prometteurs et un défi complexe. Il est donc essentiel de\n\ntrouver un équilibre entre innovation et controle pour garantir son usage bénéfique å l'ensemble\n\nde la société.\n\nD'après www.ia-info.fr- Le portail d'informations dédié à l'intelligence Artificielle, août 2025\n\nQUESTIONS (06 points)\n\nA-\n\nCOMPRÉHENSION (04 points)\n\n1)\n\nldentifie le thème abordé dans ce texte. (2 points)\n\n2)\n\nRelève deux avantages de I'Intelligence Artificielle mentionnés dans le texte.\n\n(2 points)\n\nB-\n\nVOCABULAIRE (2 ponits)\n\nExplique en contexte l'expression développement cognitif\" dans la phrase :\"Elle contribute\n\nàl'apprentissage et au développement cognitif chez l'ëtre humain.\"\n\nII\n\nRÉSUMÉ (14 points)\n\nRésume ce texte de 279 mots au l/3 de son volume initial. Une marge de plus ou moins 10 %\n\nest tolérée.\n\n2",
  "metadata": {
    "source": "fomesoutra",
    "pdfFile": "t_l_charger_download.pdf",
    "year": 2026,
    "zone": null,
    "hasCorrection": false
  }
}